{"epoch": 0, "eta": 1473741.4325, "loss": 0.1877, "lr": 0.001, "params": 419403, "time_iter": 14.4667, "accuracy": 0.9615, "precision": 0.0526, "recall": 0.0016, "f1": 0.0031, "auc": 0.5583}
{"epoch": 1, "eta": 1436526.3725, "loss": 0.1552, "lr": 0.001, "params": 419403, "time_iter": 14.0239, "accuracy": 0.9626, "precision": 0.0, "recall": 0.0, "f1": 0.0, "auc": 0.6374}
{"epoch": 2, "eta": 1418641.209, "loss": 0.1536, "lr": 0.001, "params": 419403, "time_iter": 14.1483, "accuracy": 0.9626, "precision": 0.0, "recall": 0.0, "f1": 0.0, "auc": 0.661}
{"epoch": 3, "eta": 1414708.1062, "loss": 0.1522, "lr": 0.001, "params": 419403, "time_iter": 14.6459, "accuracy": 0.9625, "precision": 0.0, "recall": 0.0, "f1": 0.0, "auc": 0.6661}
{"epoch": 4, "eta": 1395876.2056, "loss": 0.1519, "lr": 0.001, "params": 419403, "time_iter": 14.1118, "accuracy": 0.9625, "precision": 0.3333, "recall": 0.0008, "f1": 0.0016, "auc": 0.6602}
{"epoch": 5, "eta": 1380974.1783, "loss": 0.1501, "lr": 0.001, "params": 419403, "time_iter": 14.2664, "accuracy": 0.9625, "precision": 0.0, "recall": 0.0, "f1": 0.0, "auc": 0.6828}
{"epoch": 6, "eta": 1364999.328, "loss": 0.1488, "lr": 0.001, "params": 419403, "time_iter": 14.1833, "accuracy": 0.9625, "precision": 0.0, "recall": 0.0, "f1": 0.0, "auc": 0.6914}
{"epoch": 7, "eta": 1349694.5025, "loss": 0.1492, "lr": 0.001, "params": 419403, "time_iter": 14.2107, "accuracy": 0.9625, "precision": 0.3333, "recall": 0.0016, "f1": 0.0032, "auc": 0.6942}
{"epoch": 8, "eta": 1332905.3226, "loss": 0.1479, "lr": 0.001, "params": 419403, "time_iter": 14.0535, "accuracy": 0.9625, "precision": 0.2, "recall": 0.0008, "f1": 0.0016, "auc": 0.7013}
{"epoch": 9, "eta": 1320865.3393, "loss": 0.1484, "lr": 0.001, "params": 419403, "time_iter": 14.516, "accuracy": 0.9624, "precision": 0.1429, "recall": 0.0008, "f1": 0.0016, "auc": 0.7}
{"epoch": 10, "eta": 1308500.9793, "loss": 0.1464, "lr": 0.001, "params": 419403, "time_iter": 14.5404, "accuracy": 0.9624, "precision": 0.2222, "recall": 0.0016, "f1": 0.0032, "auc": 0.7137}
{"epoch": 11, "eta": 1293202.5019, "loss": 0.146, "lr": 0.001, "params": 419403, "time_iter": 14.2089, "accuracy": 0.9623, "precision": 0.1, "recall": 0.0008, "f1": 0.0016, "auc": 0.7213}
{"epoch": 12, "eta": 1279007.272, "loss": 0.1466, "lr": 0.001, "params": 419403, "time_iter": 14.354, "accuracy": 0.9622, "precision": 0.1579, "recall": 0.0024, "f1": 0.0048, "auc": 0.7127}
{"epoch": 13, "eta": 1263500.3027, "loss": 0.148, "lr": 0.001, "params": 419403, "time_iter": 14.1594, "accuracy": 0.9622, "precision": 0.2105, "recall": 0.0032, "f1": 0.0064, "auc": 0.6941}
{"epoch": 14, "eta": 1248632.6177, "loss": 0.1481, "lr": 0.001, "params": 419403, "time_iter": 14.2477, "accuracy": 0.9623, "precision": 0.32, "recall": 0.0065, "f1": 0.0127, "auc": 0.6927}
{"epoch": 15, "eta": 1235017.1077, "loss": 0.1483, "lr": 0.001, "params": 419403, "time_iter": 14.4747, "accuracy": 0.9621, "precision": 0.2308, "recall": 0.0049, "f1": 0.0095, "auc": 0.6932}
{"epoch": 16, "eta": 1220994.538, "loss": 0.1474, "lr": 0.001, "params": 419403, "time_iter": 14.4236, "accuracy": 0.9622, "precision": 0.1905, "recall": 0.0032, "f1": 0.0064, "auc": 0.7001}
{"epoch": 17, "eta": 1206167.0538, "loss": 0.1471, "lr": 0.001, "params": 419403, "time_iter": 14.2713, "accuracy": 0.9621, "precision": 0.1429, "recall": 0.0024, "f1": 0.0048, "auc": 0.7053}
{"epoch": 18, "eta": 1190631.2427, "loss": 0.1473, "lr": 0.001, "params": 419403, "time_iter": 14.1064, "accuracy": 0.9622, "precision": 0.2609, "recall": 0.0049, "f1": 0.0096, "auc": 0.7023}
{"epoch": 19, "eta": 1176135.9394, "loss": 0.1485, "lr": 0.001, "params": 419403, "time_iter": 14.3344, "accuracy": 0.9626, "precision": 0.5, "recall": 0.0008, "f1": 0.0016, "auc": 0.6959}
{"epoch": 20, "eta": 1161199.5861, "loss": 0.146, "lr": 0.001, "params": 419403, "time_iter": 14.2267, "accuracy": 0.9625, "precision": 0.3636, "recall": 0.0032, "f1": 0.0064, "auc": 0.7045}
{"epoch": 21, "eta": 1145985.285, "loss": 0.1464, "lr": 0.001, "params": 419403, "time_iter": 14.1432, "accuracy": 0.9624, "precision": 0.3333, "recall": 0.0041, "f1": 0.008, "auc": 0.7094}
{"epoch": 22, "eta": 1130221.4267, "loss": 0.1481, "lr": 0.001, "params": 419403, "time_iter": 13.9669, "accuracy": 0.9622, "precision": 0.1333, "recall": 0.0016, "f1": 0.0032, "auc": 0.7006}
{"epoch": 23, "eta": 1114334.1774, "loss": 0.1478, "lr": 0.001, "params": 419403, "time_iter": 13.8935, "accuracy": 0.9623, "precision": 0.1818, "recall": 0.0016, "f1": 0.0032, "auc": 0.7098}
{"epoch": 24, "eta": 1099922.933, "loss": 0.1461, "lr": 0.001, "params": 419403, "time_iter": 14.3304, "accuracy": 0.9623, "precision": 0.0, "recall": 0.0, "f1": 0.0, "auc": 0.7169}
{"epoch": 25, "eta": 1084648.3993, "loss": 0.146, "lr": 0.001, "params": 419403, "time_iter": 14.0444, "accuracy": 0.9623, "precision": 0.1429, "recall": 0.0016, "f1": 0.0032, "auc": 0.7158}
{"epoch": 26, "eta": 1069634.0754, "loss": 0.1458, "lr": 0.001, "params": 419403, "time_iter": 14.116, "accuracy": 0.9622, "precision": 0.0714, "recall": 0.0008, "f1": 0.0016, "auc": 0.7137}
{"epoch": 27, "eta": 1055879.6363, "loss": 0.1467, "lr": 0.001, "params": 419403, "time_iter": 14.579, "accuracy": 0.9623, "precision": 0.2, "recall": 0.0024, "f1": 0.0048, "auc": 0.7153}
{"epoch": 28, "eta": 1040836.3193, "loss": 0.1467, "lr": 0.001, "params": 419403, "time_iter": 14.1015, "accuracy": 0.9623, "precision": 0.2778, "recall": 0.0041, "f1": 0.008, "auc": 0.7106}
{"epoch": 29, "eta": 1025295.8812, "loss": 0.1475, "lr": 0.001, "params": 419403, "time_iter": 13.8797, "accuracy": 0.9622, "precision": 0.0769, "recall": 0.0008, "f1": 0.0016, "auc": 0.707}
{"epoch": 30, "eta": 1010659.235, "loss": 0.1471, "lr": 0.001, "params": 419403, "time_iter": 14.2388, "accuracy": 0.9622, "precision": 0.0714, "recall": 0.0008, "f1": 0.0016, "auc": 0.7097}
{"epoch": 31, "eta": 996258.789, "loss": 0.1489, "lr": 0.001, "params": 419403, "time_iter": 14.3473, "accuracy": 0.9619, "precision": 0.2105, "recall": 0.0065, "f1": 0.0126, "auc": 0.6918}
{"epoch": 32, "eta": 981142.6149, "loss": 0.1485, "lr": 0.001, "params": 419403, "time_iter": 14.0152, "accuracy": 0.9622, "precision": 0.1905, "recall": 0.0032, "f1": 0.0064, "auc": 0.6875}
{"epoch": 33, "eta": 966550.9851, "loss": 0.1485, "lr": 0.001, "params": 419403, "time_iter": 14.2574, "accuracy": 0.9622, "precision": 0.1176, "recall": 0.0016, "f1": 0.0032, "auc": 0.6897}
{"epoch": 34, "eta": 952705.7801, "loss": 0.1477, "lr": 0.001, "params": 419403, "time_iter": 14.6504, "accuracy": 0.9622, "precision": 0.125, "recall": 0.0016, "f1": 0.0032, "auc": 0.702}
{"epoch": 35, "eta": 938054.1131, "loss": 0.148, "lr": 0.001, "params": 419403, "time_iter": 14.2469, "accuracy": 0.9624, "precision": 0.2, "recall": 0.0016, "f1": 0.0032, "auc": 0.6986}
{"epoch": 36, "eta": 922929.9022, "loss": 0.1466, "lr": 0.001, "params": 419403, "time_iter": 13.9774, "accuracy": 0.9623, "precision": 0.1818, "recall": 0.0016, "f1": 0.0032, "auc": 0.7071}
{"epoch": 37, "eta": 909074.5156, "loss": 0.1462, "lr": 0.001, "params": 419403, "time_iter": 14.7099, "accuracy": 0.9622, "precision": 0.125, "recall": 0.0016, "f1": 0.0032, "auc": 0.7097}
{"epoch": 38, "eta": 895067.1587, "loss": 0.1458, "lr": 0.001, "params": 419403, "time_iter": 14.6563, "accuracy": 0.9622, "precision": 0.1176, "recall": 0.0016, "f1": 0.0032, "auc": 0.7112}
{"epoch": 39, "eta": 880037.1557, "loss": 0.1456, "lr": 0.001, "params": 419403, "time_iter": 14.0286, "accuracy": 0.9621, "precision": 0.1111, "recall": 0.0016, "f1": 0.0032, "auc": 0.7154}
{"epoch": 40, "eta": 865561.8269, "loss": 0.1456, "lr": 0.001, "params": 419403, "time_iter": 14.3836, "accuracy": 0.962, "precision": 0.125, "recall": 0.0024, "f1": 0.0048, "auc": 0.7129}
{"epoch": 41, "eta": 851143.8334, "loss": 0.1458, "lr": 0.001, "params": 419403, "time_iter": 14.4348, "accuracy": 0.9621, "precision": 0.1739, "recall": 0.0032, "f1": 0.0064, "auc": 0.7085}
{"epoch": 42, "eta": 836119.9302, "loss": 0.1456, "lr": 0.001, "params": 419403, "time_iter": 14.0054, "accuracy": 0.9621, "precision": 0.1667, "recall": 0.0032, "f1": 0.0064, "auc": 0.7097}
{"epoch": 43, "eta": 821075.5217, "loss": 0.1454, "lr": 0.001, "params": 419403, "time_iter": 13.9685, "accuracy": 0.9622, "precision": 0.125, "recall": 0.0016, "f1": 0.0032, "auc": 0.7076}
{"epoch": 44, "eta": 806237.0273, "loss": 0.1456, "lr": 0.001, "params": 419403, "time_iter": 14.1086, "accuracy": 0.9621, "precision": 0.2333, "recall": 0.0057, "f1": 0.0111, "auc": 0.7111}
{"epoch": 45, "eta": 792098.9429, "loss": 0.1471, "lr": 0.001, "params": 419403, "time_iter": 14.6768, "accuracy": 0.962, "precision": 0.1724, "recall": 0.0041, "f1": 0.0079, "auc": 0.7035}
{"epoch": 46, "eta": 778233.7731, "loss": 0.1467, "lr": 0.001, "params": 419403, "time_iter": 14.9474, "accuracy": 0.962, "precision": 0.087, "recall": 0.0016, "f1": 0.0032, "auc": 0.7093}
{"epoch": 47, "eta": 764243.175, "loss": 0.1457, "lr": 0.001, "params": 419403, "time_iter": 14.8915, "accuracy": 0.962, "precision": 0.16, "recall": 0.0032, "f1": 0.0064, "auc": 0.7151}
{"epoch": 48, "eta": 749797.8461, "loss": 0.1458, "lr": 0.001, "params": 419403, "time_iter": 14.5178, "accuracy": 0.9622, "precision": 0.2273, "recall": 0.0041, "f1": 0.008, "auc": 0.7155}
{"epoch": 49, "eta": 735356.2614, "loss": 0.1456, "lr": 0.001, "params": 419403, "time_iter": 14.5406, "accuracy": 0.9621, "precision": 0.2143, "recall": 0.0049, "f1": 0.0095, "auc": 0.7187}
{"epoch": 50, "eta": 720711.8719, "loss": 0.1456, "lr": 0.001, "params": 419403, "time_iter": 14.3561, "accuracy": 0.9617, "precision": 0.1778, "recall": 0.0065, "f1": 0.0125, "auc": 0.7196}
{"epoch": 51, "eta": 706092.4789, "loss": 0.1461, "lr": 0.001, "params": 419403, "time_iter": 14.3876, "accuracy": 0.9618, "precision": 0.175, "recall": 0.0057, "f1": 0.011, "auc": 0.7154}
{"epoch": 52, "eta": 691139.7453, "loss": 0.1453, "lr": 0.001, "params": 419403, "time_iter": 14.03, "accuracy": 0.9617, "precision": 0.2545, "recall": 0.0114, "f1": 0.0218, "auc": 0.7191}
{"epoch": 53, "eta": 676318.171, "loss": 0.1467, "lr": 0.001, "params": 419403, "time_iter": 14.1578, "accuracy": 0.9621, "precision": 0.3171, "recall": 0.0106, "f1": 0.0204, "auc": 0.7083}
{"epoch": 54, "eta": 661649.7499, "loss": 0.1452, "lr": 0.001, "params": 419403, "time_iter": 14.3288, "accuracy": 0.962, "precision": 0.1481, "recall": 0.0032, "f1": 0.0064, "auc": 0.7194}
{"epoch": 55, "eta": 646715.8252, "loss": 0.1449, "lr": 0.001, "params": 419403, "time_iter": 14.0037, "accuracy": 0.9618, "precision": 0.2093, "recall": 0.0073, "f1": 0.0141, "auc": 0.7209}
{"epoch": 56, "eta": 632252.7262, "loss": 0.1448, "lr": 0.001, "params": 419403, "time_iter": 14.5866, "accuracy": 0.9619, "precision": 0.1379, "recall": 0.0032, "f1": 0.0063, "auc": 0.7253}
{"epoch": 57, "eta": 617730.6728, "loss": 0.1449, "lr": 0.001, "params": 419403, "time_iter": 14.5327, "accuracy": 0.962, "precision": 0.2632, "recall": 0.0081, "f1": 0.0157, "auc": 0.7231}
{"epoch": 58, "eta": 603321.4127, "loss": 0.1461, "lr": 0.001, "params": 419403, "time_iter": 14.711, "accuracy": 0.962, "precision": 0.2424, "recall": 0.0065, "f1": 0.0126, "auc": 0.7137}
{"epoch": 59, "eta": 588463.4676, "loss": 0.1461, "lr": 0.001, "params": 419403, "time_iter": 14.0923, "accuracy": 0.962, "precision": 0.2821, "recall": 0.0089, "f1": 0.0173, "auc": 0.7129}
{"epoch": 60, "eta": 573700.68, "loss": 0.1465, "lr": 0.001, "params": 419403, "time_iter": 14.2191, "accuracy": 0.9619, "precision": 0.1714, "recall": 0.0049, "f1": 0.0095, "auc": 0.7126}
{"epoch": 61, "eta": 559136.8782, "loss": 0.1457, "lr": 0.001, "params": 419403, "time_iter": 14.5279, "accuracy": 0.9622, "precision": 0.2759, "recall": 0.0065, "f1": 0.0127, "auc": 0.7171}
{"epoch": 62, "eta": 544086.0895, "loss": 0.1453, "lr": 0.001, "params": 419403, "time_iter": 13.7424, "accuracy": 0.9619, "precision": 0.1875, "recall": 0.0049, "f1": 0.0095, "auc": 0.7219}
{"epoch": 63, "eta": 529293.9006, "loss": 0.1446, "lr": 0.001, "params": 419403, "time_iter": 14.14, "accuracy": 0.962, "precision": 0.2121, "recall": 0.0057, "f1": 0.0111, "auc": 0.7273}
{"epoch": 64, "eta": 514672.0799, "loss": 0.1449, "lr": 0.001, "params": 419403, "time_iter": 14.4341, "accuracy": 0.9618, "precision": 0.25, "recall": 0.0097, "f1": 0.0188, "auc": 0.7269}
{"epoch": 65, "eta": 499612.8637, "loss": 0.1449, "lr": 0.001, "params": 419403, "time_iter": 13.6221, "accuracy": 0.9618, "precision": 0.1471, "recall": 0.0041, "f1": 0.0079, "auc": 0.7281}
{"epoch": 66, "eta": 484746.8389, "loss": 0.1436, "lr": 0.001, "params": 419403, "time_iter": 13.9419, "accuracy": 0.9618, "precision": 0.2174, "recall": 0.0081, "f1": 0.0156, "auc": 0.7328}
{"epoch": 67, "eta": 469878.5062, "loss": 0.1437, "lr": 0.001, "params": 419403, "time_iter": 13.9056, "accuracy": 0.962, "precision": 0.2188, "recall": 0.0057, "f1": 0.0111, "auc": 0.7339}
{"epoch": 68, "eta": 455190.4295, "loss": 0.1436, "lr": 0.001, "params": 419403, "time_iter": 14.2604, "accuracy": 0.962, "precision": 0.2857, "recall": 0.0097, "f1": 0.0188, "auc": 0.733}
{"epoch": 69, "eta": 440547.8305, "loss": 0.1439, "lr": 0.001, "params": 419403, "time_iter": 14.3626, "accuracy": 0.9619, "precision": 0.2195, "recall": 0.0073, "f1": 0.0141, "auc": 0.7319}
{"epoch": 70, "eta": 425801.8736, "loss": 0.1442, "lr": 0.001, "params": 419403, "time_iter": 14.1259, "accuracy": 0.962, "precision": 0.275, "recall": 0.0089, "f1": 0.0173, "auc": 0.7267}
{"epoch": 71, "eta": 411174.0457, "loss": 0.1438, "lr": 0.001, "params": 419403, "time_iter": 14.4065, "accuracy": 0.9618, "precision": 0.2391, "recall": 0.0089, "f1": 0.0172, "auc": 0.7285}
{"epoch": 72, "eta": 396160.8465, "loss": 0.1438, "lr": 0.001, "params": 419403, "time_iter": 13.408, "accuracy": 0.9618, "precision": 0.2045, "recall": 0.0073, "f1": 0.0141, "auc": 0.733}
{"epoch": 73, "eta": 381246.2053, "loss": 0.1452, "lr": 0.001, "params": 419403, "time_iter": 13.5897, "accuracy": 0.9619, "precision": 0.2917, "recall": 0.0114, "f1": 0.0219, "auc": 0.7254}
{"epoch": 74, "eta": 366395.8001, "loss": 0.1458, "lr": 0.001, "params": 419403, "time_iter": 13.7046, "accuracy": 0.962, "precision": 0.2632, "recall": 0.0081, "f1": 0.0157, "auc": 0.717}
{"epoch": 75, "eta": 351634.4288, "loss": 0.1444, "lr": 0.001, "params": 419403, "time_iter": 13.918, "accuracy": 0.9618, "precision": 0.2549, "recall": 0.0106, "f1": 0.0203, "auc": 0.7246}
{"epoch": 76, "eta": 336673.7341, "loss": 0.145, "lr": 0.001, "params": 419403, "time_iter": 13.2323, "accuracy": 0.962, "precision": 0.3023, "recall": 0.0106, "f1": 0.0204, "auc": 0.7228}
{"epoch": 77, "eta": 322005.6186, "loss": 0.145, "lr": 0.001, "params": 419403, "time_iter": 14.1216, "accuracy": 0.9619, "precision": 0.283, "recall": 0.0122, "f1": 0.0233, "auc": 0.7149}
{"epoch": 78, "eta": 307329.757, "loss": 0.1453, "lr": 0.001, "params": 419403, "time_iter": 14.0807, "accuracy": 0.9618, "precision": 0.2593, "recall": 0.0114, "f1": 0.0218, "auc": 0.7166}
{"epoch": 79, "eta": 292721.3649, "loss": 0.1453, "lr": 0.001, "params": 419403, "time_iter": 14.3248, "accuracy": 0.962, "precision": 0.2857, "recall": 0.0097, "f1": 0.0188, "auc": 0.7108}
{"epoch": 80, "eta": 278070.574, "loss": 0.1452, "lr": 0.001, "params": 419403, "time_iter": 14.1626, "accuracy": 0.9621, "precision": 0.2, "recall": 0.0041, "f1": 0.008, "auc": 0.715}
{"epoch": 81, "eta": 263444.7876, "loss": 0.1445, "lr": 0.001, "params": 419403, "time_iter": 14.2649, "accuracy": 0.9622, "precision": 0.1905, "recall": 0.0032, "f1": 0.0064, "auc": 0.7152}
{"epoch": 82, "eta": 248963.5857, "loss": 0.144, "lr": 0.001, "params": 419403, "time_iter": 14.957, "accuracy": 0.962, "precision": 0.2632, "recall": 0.0081, "f1": 0.0157, "auc": 0.7274}
{"epoch": 83, "eta": 234195.4066, "loss": 0.1444, "lr": 0.001, "params": 419403, "time_iter": 13.6033, "accuracy": 0.9619, "precision": 0.1765, "recall": 0.0049, "f1": 0.0095, "auc": 0.7223}
{"epoch": 84, "eta": 219590.9275, "loss": 0.1445, "lr": 0.001, "params": 419403, "time_iter": 14.405, "accuracy": 0.9618, "precision": 0.1667, "recall": 0.0049, "f1": 0.0095, "auc": 0.7181}
{"epoch": 85, "eta": 204896.1939, "loss": 0.1457, "lr": 0.001, "params": 419403, "time_iter": 13.8965, "accuracy": 0.9622, "precision": 0.2174, "recall": 0.0041, "f1": 0.008, "auc": 0.71}
{"epoch": 86, "eta": 190251.802, "loss": 0.1453, "lr": 0.001, "params": 419403, "time_iter": 14.1648, "accuracy": 0.9619, "precision": 0.2051, "recall": 0.0065, "f1": 0.0126, "auc": 0.7086}
{"epoch": 87, "eta": 175644.9434, "loss": 0.1445, "lr": 0.001, "params": 419403, "time_iter": 14.4211, "accuracy": 0.9616, "precision": 0.2222, "recall": 0.0097, "f1": 0.0187, "auc": 0.7215}
{"epoch": 88, "eta": 161022.2334, "loss": 0.1439, "lr": 0.001, "params": 419403, "time_iter": 14.3375, "accuracy": 0.9618, "precision": 0.25, "recall": 0.0097, "f1": 0.0188, "auc": 0.7233}
{"epoch": 89, "eta": 146332.4147, "loss": 0.1438, "lr": 0.001, "params": 419403, "time_iter": 13.776, "accuracy": 0.9617, "precision": 0.2157, "recall": 0.0089, "f1": 0.0171, "auc": 0.7248}
{"epoch": 90, "eta": 131675.3233, "loss": 0.1447, "lr": 0.001, "params": 419403, "time_iter": 13.9865, "accuracy": 0.9621, "precision": 0.2, "recall": 0.0041, "f1": 0.008, "auc": 0.7215}
{"epoch": 91, "eta": 117015.6634, "loss": 0.1454, "lr": 0.001, "params": 419403, "time_iter": 13.8934, "accuracy": 0.9622, "precision": 0.3103, "recall": 0.0073, "f1": 0.0143, "auc": 0.7163}
{"epoch": 92, "eta": 102405.0042, "loss": 0.1467, "lr": 0.001, "params": 419403, "time_iter": 14.4252, "accuracy": 0.962, "precision": 0.1304, "recall": 0.0024, "f1": 0.0048, "auc": 0.7031}
{"epoch": 93, "eta": 87736.1048, "loss": 0.1463, "lr": 0.001, "params": 419403, "time_iter": 13.6139, "accuracy": 0.9619, "precision": 0.25, "recall": 0.0089, "f1": 0.0172, "auc": 0.7069}
{"epoch": 94, "eta": 73098.7262, "loss": 0.1456, "lr": 0.001, "params": 419403, "time_iter": 13.9393, "accuracy": 0.9616, "precision": 0.1739, "recall": 0.0065, "f1": 0.0125, "auc": 0.7084}
{"epoch": 95, "eta": 58475.6043, "loss": 0.1453, "lr": 0.001, "params": 419403, "time_iter": 14.129, "accuracy": 0.9618, "precision": 0.2273, "recall": 0.0081, "f1": 0.0157, "auc": 0.7111}
{"epoch": 96, "eta": 43852.1759, "loss": 0.1453, "lr": 0.001, "params": 419403, "time_iter": 14.0646, "accuracy": 0.9619, "precision": 0.2745, "recall": 0.0114, "f1": 0.0218, "auc": 0.712}
{"epoch": 97, "eta": 29230.5509, "loss": 0.1453, "lr": 0.001, "params": 419403, "time_iter": 14.0039, "accuracy": 0.9619, "precision": 0.2609, "recall": 0.0097, "f1": 0.0188, "auc": 0.7094}
{"epoch": 98, "eta": 14615.17, "loss": 0.145, "lr": 0.001, "params": 419403, "time_iter": 14.1932, "accuracy": 0.9619, "precision": 0.2917, "recall": 0.0114, "f1": 0.0219, "auc": 0.7154}
{"epoch": 99, "eta": 0.0, "loss": 0.1455, "lr": 0.001, "params": 419403, "time_iter": 14.5679, "accuracy": 0.9619, "precision": 0.2619, "recall": 0.0089, "f1": 0.0173, "auc": 0.712}
