{"epoch": 0, "eta": 1330396.693, "loss": 0.2098, "lr": 0.001, "params": 600603, "time_iter": 13.0596, "accuracy": 0.9626, "precision": 0.0, "recall": 0.0, "f1": 0.0, "auc": 0.5273}
{"epoch": 1, "eta": 1318290.0493, "loss": 0.1563, "lr": 0.001, "params": 600603, "time_iter": 13.086, "accuracy": 0.9626, "precision": 0.0, "recall": 0.0, "f1": 0.0, "auc": 0.6217}
{"epoch": 2, "eta": 1307758.9985, "loss": 0.1522, "lr": 0.001, "params": 600603, "time_iter": 13.1606, "accuracy": 0.9626, "precision": 0.0, "recall": 0.0, "f1": 0.0, "auc": 0.6736}
{"epoch": 3, "eta": 1292703.3324, "loss": 0.1489, "lr": 0.001, "params": 600603, "time_iter": 13.0384, "accuracy": 0.9626, "precision": 0.0, "recall": 0.0, "f1": 0.0, "auc": 0.6984}
{"epoch": 4, "eta": 1280330.9923, "loss": 0.1477, "lr": 0.001, "params": 600603, "time_iter": 13.1421, "accuracy": 0.9626, "precision": 0.0, "recall": 0.0, "f1": 0.0, "auc": 0.7095}
{"epoch": 5, "eta": 1267645.8726, "loss": 0.1456, "lr": 0.001, "params": 600603, "time_iter": 13.1465, "accuracy": 0.9626, "precision": 0.0, "recall": 0.0, "f1": 0.0, "auc": 0.7267}
{"epoch": 6, "eta": 1253516.4561, "loss": 0.1445, "lr": 0.001, "params": 600603, "time_iter": 13.0584, "accuracy": 0.9626, "precision": 0.0, "recall": 0.0, "f1": 0.0, "auc": 0.7332}
{"epoch": 7, "eta": 1240457.4447, "loss": 0.1424, "lr": 0.001, "params": 600603, "time_iter": 13.1343, "accuracy": 0.9626, "precision": 0.0, "recall": 0.0, "f1": 0.0, "auc": 0.7435}
{"epoch": 8, "eta": 1227908.7187, "loss": 0.1417, "lr": 0.001, "params": 600603, "time_iter": 13.1931, "accuracy": 0.9626, "precision": 0.0, "recall": 0.0, "f1": 0.0, "auc": 0.7438}
{"epoch": 9, "eta": 1212233.8985, "loss": 0.142, "lr": 0.001, "params": 600603, "time_iter": 12.8777, "accuracy": 0.9626, "precision": 0.0, "recall": 0.0, "f1": 0.0, "auc": 0.7442}
{"epoch": 10, "eta": 1198028.1886, "loss": 0.1399, "lr": 0.001, "params": 600603, "time_iter": 13.0012, "accuracy": 0.9626, "precision": 0.0, "recall": 0.0, "f1": 0.0, "auc": 0.7579}
{"epoch": 11, "eta": 1185557.3103, "loss": 0.142, "lr": 0.001, "params": 600603, "time_iter": 13.2128, "accuracy": 0.9625, "precision": 0.0, "recall": 0.0, "f1": 0.0, "auc": 0.7474}
{"epoch": 12, "eta": 1171611.4947, "loss": 0.1402, "lr": 0.001, "params": 600603, "time_iter": 13.0238, "accuracy": 0.9625, "precision": 0.2857, "recall": 0.0016, "f1": 0.0032, "auc": 0.7537}
{"epoch": 13, "eta": 1159314.1777, "loss": 0.1392, "lr": 0.001, "params": 600603, "time_iter": 13.2723, "accuracy": 0.9623, "precision": 0.2353, "recall": 0.0032, "f1": 0.0064, "auc": 0.755}
{"epoch": 14, "eta": 1145028.0605, "loss": 0.1386, "lr": 0.001, "params": 600603, "time_iter": 12.9623, "accuracy": 0.9623, "precision": 0.1538, "recall": 0.0016, "f1": 0.0032, "auc": 0.7637}
{"epoch": 15, "eta": 1130890.8837, "loss": 0.139, "lr": 0.001, "params": 600603, "time_iter": 12.9679, "accuracy": 0.9624, "precision": 0.3333, "recall": 0.0049, "f1": 0.0096, "auc": 0.7597}
{"epoch": 16, "eta": 1117907.3287, "loss": 0.1383, "lr": 0.001, "params": 600603, "time_iter": 13.179, "accuracy": 0.9623, "precision": 0.3333, "recall": 0.0065, "f1": 0.0127, "auc": 0.7581}
{"epoch": 17, "eta": 1104680.9068, "loss": 0.1358, "lr": 0.001, "params": 600603, "time_iter": 13.1409, "accuracy": 0.9625, "precision": 0.4483, "recall": 0.0106, "f1": 0.0206, "auc": 0.7679}
{"epoch": 18, "eta": 1090553.6983, "loss": 0.1343, "lr": 0.001, "params": 600603, "time_iter": 12.9426, "accuracy": 0.9626, "precision": 0.5, "recall": 0.0179, "f1": 0.0345, "auc": 0.7753}
{"epoch": 19, "eta": 1077267.4973, "loss": 0.1351, "lr": 0.001, "params": 600603, "time_iter": 13.1273, "accuracy": 0.9623, "precision": 0.4231, "recall": 0.0179, "f1": 0.0343, "auc": 0.7705}
{"epoch": 20, "eta": 1063795.0199, "loss": 0.1372, "lr": 0.001, "params": 600603, "time_iter": 13.0846, "accuracy": 0.9621, "precision": 0.325, "recall": 0.0106, "f1": 0.0204, "auc": 0.7667}
{"epoch": 21, "eta": 1050178.9563, "loss": 0.1358, "lr": 0.001, "params": 600603, "time_iter": 13.0451, "accuracy": 0.9622, "precision": 0.3966, "recall": 0.0187, "f1": 0.0357, "auc": 0.7687}
{"epoch": 22, "eta": 1037042.8723, "loss": 0.1394, "lr": 0.001, "params": 600603, "time_iter": 13.1795, "accuracy": 0.9622, "precision": 0.4, "recall": 0.0211, "f1": 0.0401, "auc": 0.755}
{"epoch": 23, "eta": 1023364.1753, "loss": 0.137, "lr": 0.001, "params": 600603, "time_iter": 13.0239, "accuracy": 0.9619, "precision": 0.3333, "recall": 0.017, "f1": 0.0324, "auc": 0.7639}
{"epoch": 24, "eta": 1010073.4206, "loss": 0.136, "lr": 0.001, "params": 600603, "time_iter": 13.1424, "accuracy": 0.9623, "precision": 0.4286, "recall": 0.0195, "f1": 0.0373, "auc": 0.7622}
{"epoch": 25, "eta": 996526.1939, "loss": 0.1348, "lr": 0.001, "params": 600603, "time_iter": 13.0609, "accuracy": 0.9624, "precision": 0.4615, "recall": 0.0292, "f1": 0.055, "auc": 0.7589}
{"epoch": 26, "eta": 983207.7198, "loss": 0.1344, "lr": 0.001, "params": 600603, "time_iter": 13.1403, "accuracy": 0.9622, "precision": 0.4211, "recall": 0.026, "f1": 0.0489, "auc": 0.763}
{"epoch": 27, "eta": 970236.6762, "loss": 0.1344, "lr": 0.001, "params": 600603, "time_iter": 13.2771, "accuracy": 0.9625, "precision": 0.4868, "recall": 0.03, "f1": 0.0566, "auc": 0.7617}
{"epoch": 28, "eta": 956985.8345, "loss": 0.1338, "lr": 0.001, "params": 600603, "time_iter": 13.1849, "accuracy": 0.9624, "precision": 0.4731, "recall": 0.0357, "f1": 0.0664, "auc": 0.7658}
{"epoch": 29, "eta": 943158.4069, "loss": 0.135, "lr": 0.001, "params": 600603, "time_iter": 12.9536, "accuracy": 0.9623, "precision": 0.4632, "recall": 0.0357, "f1": 0.0663, "auc": 0.7643}
{"epoch": 30, "eta": 929463.0169, "loss": 0.1349, "lr": 0.001, "params": 600603, "time_iter": 12.9972, "accuracy": 0.9628, "precision": 0.5385, "recall": 0.0398, "f1": 0.0741, "auc": 0.7686}
{"epoch": 31, "eta": 915975.9396, "loss": 0.1336, "lr": 0.001, "params": 600603, "time_iter": 13.0833, "accuracy": 0.9622, "precision": 0.4409, "recall": 0.0333, "f1": 0.0619, "auc": 0.775}
{"epoch": 32, "eta": 902339.0125, "loss": 0.1323, "lr": 0.001, "params": 600603, "time_iter": 13.0108, "accuracy": 0.9626, "precision": 0.5047, "recall": 0.0438, "f1": 0.0807, "auc": 0.7733}
{"epoch": 33, "eta": 888962.7541, "loss": 0.133, "lr": 0.001, "params": 600603, "time_iter": 13.134, "accuracy": 0.9625, "precision": 0.4954, "recall": 0.0438, "f1": 0.0805, "auc": 0.7755}
{"epoch": 34, "eta": 875424.2295, "loss": 0.1341, "lr": 0.001, "params": 600603, "time_iter": 13.0532, "accuracy": 0.9623, "precision": 0.4624, "recall": 0.0349, "f1": 0.0649, "auc": 0.7703}
{"epoch": 35, "eta": 861935.0597, "loss": 0.1328, "lr": 0.001, "params": 600603, "time_iter": 13.077, "accuracy": 0.9627, "precision": 0.5254, "recall": 0.0503, "f1": 0.0919, "auc": 0.7703}
{"epoch": 36, "eta": 848515.851, "loss": 0.1326, "lr": 0.001, "params": 600603, "time_iter": 13.1159, "accuracy": 0.963, "precision": 0.5625, "recall": 0.0511, "f1": 0.0938, "auc": 0.7722}
{"epoch": 37, "eta": 834961.8925, "loss": 0.1349, "lr": 0.001, "params": 600603, "time_iter": 13.038, "accuracy": 0.9619, "precision": 0.3895, "recall": 0.03, "f1": 0.0558, "auc": 0.7704}
{"epoch": 38, "eta": 821125.3663, "loss": 0.1364, "lr": 0.001, "params": 600603, "time_iter": 12.8581, "accuracy": 0.9626, "precision": 0.5054, "recall": 0.0381, "f1": 0.0709, "auc": 0.7633}
{"epoch": 39, "eta": 807488.3092, "loss": 0.1362, "lr": 0.001, "params": 600603, "time_iter": 12.9677, "accuracy": 0.9624, "precision": 0.4787, "recall": 0.0365, "f1": 0.0679, "auc": 0.7654}
{"epoch": 40, "eta": 794116.6655, "loss": 0.1347, "lr": 0.001, "params": 600603, "time_iter": 13.1373, "accuracy": 0.9621, "precision": 0.4271, "recall": 0.0333, "f1": 0.0617, "auc": 0.7688}
{"epoch": 41, "eta": 780540.2358, "loss": 0.1356, "lr": 0.001, "params": 600603, "time_iter": 12.9981, "accuracy": 0.9623, "precision": 0.4494, "recall": 0.0325, "f1": 0.0606, "auc": 0.7695}
{"epoch": 42, "eta": 766959.4098, "loss": 0.1346, "lr": 0.001, "params": 600603, "time_iter": 12.988, "accuracy": 0.9624, "precision": 0.4783, "recall": 0.0357, "f1": 0.0665, "auc": 0.7688}
{"epoch": 43, "eta": 753423.4921, "loss": 0.1325, "lr": 0.001, "params": 600603, "time_iter": 13.0148, "accuracy": 0.9626, "precision": 0.5042, "recall": 0.0487, "f1": 0.0888, "auc": 0.7796}
{"epoch": 44, "eta": 739862.5611, "loss": 0.1363, "lr": 0.001, "params": 600603, "time_iter": 12.9898, "accuracy": 0.9626, "precision": 0.5195, "recall": 0.0325, "f1": 0.0611, "auc": 0.7577}
{"epoch": 45, "eta": 726504.4714, "loss": 0.1339, "lr": 0.001, "params": 600603, "time_iter": 13.1507, "accuracy": 0.9627, "precision": 0.5149, "recall": 0.056, "f1": 0.101, "auc": 0.7717}
{"epoch": 46, "eta": 713001.4612, "loss": 0.1325, "lr": 0.001, "params": 600603, "time_iter": 13.0322, "accuracy": 0.963, "precision": 0.558, "recall": 0.0625, "f1": 0.1124, "auc": 0.7763}
{"epoch": 47, "eta": 699328.8756, "loss": 0.1426, "lr": 0.001, "params": 600603, "time_iter": 12.8766, "accuracy": 0.9624, "precision": 0.4697, "recall": 0.0252, "f1": 0.0478, "auc": 0.7199}
{"epoch": 48, "eta": 685774.5696, "loss": 0.1379, "lr": 0.001, "params": 600603, "time_iter": 12.9709, "accuracy": 0.9629, "precision": 0.5833, "recall": 0.0341, "f1": 0.0644, "auc": 0.7469}
{"epoch": 49, "eta": 672713.6184, "loss": 0.1356, "lr": 0.001, "params": 600603, "time_iter": 13.4423, "accuracy": 0.9631, "precision": 0.596, "recall": 0.0479, "f1": 0.0887, "auc": 0.7498}
{"epoch": 50, "eta": 659184.5887, "loss": 0.1341, "lr": 0.001, "params": 600603, "time_iter": 12.9995, "accuracy": 0.9631, "precision": 0.5714, "recall": 0.0584, "f1": 0.106, "auc": 0.7579}
{"epoch": 51, "eta": 645718.149, "loss": 0.1333, "lr": 0.001, "params": 600603, "time_iter": 13.0592, "accuracy": 0.9633, "precision": 0.5891, "recall": 0.0617, "f1": 0.1117, "auc": 0.7582}
{"epoch": 52, "eta": 632446.8388, "loss": 0.1329, "lr": 0.001, "params": 600603, "time_iter": 13.2719, "accuracy": 0.9635, "precision": 0.6071, "recall": 0.069, "f1": 0.1239, "auc": 0.766}
{"epoch": 53, "eta": 618901.531, "loss": 0.1333, "lr": 0.001, "params": 600603, "time_iter": 12.9756, "accuracy": 0.9629, "precision": 0.5442, "recall": 0.0649, "f1": 0.116, "auc": 0.7668}
{"epoch": 54, "eta": 605419.7474, "loss": 0.1339, "lr": 0.001, "params": 600603, "time_iter": 13.0427, "accuracy": 0.9631, "precision": 0.5789, "recall": 0.0536, "f1": 0.0981, "auc": 0.7751}
{"epoch": 55, "eta": 592011.5029, "loss": 0.1313, "lr": 0.001, "params": 600603, "time_iter": 13.1309, "accuracy": 0.9632, "precision": 0.5802, "recall": 0.0617, "f1": 0.1115, "auc": 0.7801}
{"epoch": 56, "eta": 578475.3902, "loss": 0.1316, "lr": 0.001, "params": 600603, "time_iter": 12.9709, "accuracy": 0.9636, "precision": 0.6241, "recall": 0.0714, "f1": 0.1282, "auc": 0.7754}
{"epoch": 57, "eta": 565028.5161, "loss": 0.1358, "lr": 0.001, "params": 600603, "time_iter": 13.0819, "accuracy": 0.9634, "precision": 0.6273, "recall": 0.056, "f1": 0.1028, "auc": 0.7604}
{"epoch": 58, "eta": 551671.8999, "loss": 0.1343, "lr": 0.001, "params": 600603, "time_iter": 13.2088, "accuracy": 0.9638, "precision": 0.6667, "recall": 0.0682, "f1": 0.1237, "auc": 0.7609}
{"epoch": 59, "eta": 538069.8676, "loss": 0.1335, "lr": 0.001, "params": 600603, "time_iter": 12.8625, "accuracy": 0.9636, "precision": 0.6357, "recall": 0.0666, "f1": 0.1205, "auc": 0.7665}
{"epoch": 60, "eta": 524596.7223, "loss": 0.1333, "lr": 0.001, "params": 600603, "time_iter": 13.0401, "accuracy": 0.964, "precision": 0.669, "recall": 0.0787, "f1": 0.1409, "auc": 0.7693}
{"epoch": 61, "eta": 511186.4173, "loss": 0.1326, "lr": 0.001, "params": 600603, "time_iter": 13.1369, "accuracy": 0.9636, "precision": 0.6138, "recall": 0.0722, "f1": 0.1293, "auc": 0.7713}
{"epoch": 62, "eta": 497749.9154, "loss": 0.1327, "lr": 0.001, "params": 600603, "time_iter": 13.0993, "accuracy": 0.9641, "precision": 0.6786, "recall": 0.0771, "f1": 0.1385, "auc": 0.7666}
{"epoch": 63, "eta": 484330.4035, "loss": 0.1331, "lr": 0.001, "params": 600603, "time_iter": 13.1309, "accuracy": 0.9638, "precision": 0.6389, "recall": 0.0747, "f1": 0.1337, "auc": 0.775}
{"epoch": 64, "eta": 470892.8697, "loss": 0.131, "lr": 0.001, "params": 600603, "time_iter": 13.1035, "accuracy": 0.9636, "precision": 0.6065, "recall": 0.0763, "f1": 0.1355, "auc": 0.7807}
{"epoch": 65, "eta": 457480.3104, "loss": 0.1294, "lr": 0.001, "params": 600603, "time_iter": 13.1532, "accuracy": 0.9639, "precision": 0.6175, "recall": 0.0917, "f1": 0.1597, "auc": 0.7833}
{"epoch": 66, "eta": 443993.4446, "loss": 0.1279, "lr": 0.001, "params": 600603, "time_iter": 13.0138, "accuracy": 0.9638, "precision": 0.6105, "recall": 0.0942, "f1": 0.1632, "auc": 0.7946}
{"epoch": 67, "eta": 430540.2967, "loss": 0.1283, "lr": 0.001, "params": 600603, "time_iter": 13.0776, "accuracy": 0.964, "precision": 0.6127, "recall": 0.1015, "f1": 0.1741, "auc": 0.7854}
{"epoch": 68, "eta": 417067.9401, "loss": 0.1298, "lr": 0.001, "params": 600603, "time_iter": 13.0363, "accuracy": 0.9641, "precision": 0.633, "recall": 0.0966, "f1": 0.1676, "auc": 0.7802}
{"epoch": 69, "eta": 403644.6465, "loss": 0.128, "lr": 0.001, "params": 600603, "time_iter": 13.1438, "accuracy": 0.9641, "precision": 0.634, "recall": 0.0998, "f1": 0.1725, "auc": 0.7905}
{"epoch": 70, "eta": 390206.5345, "loss": 0.129, "lr": 0.001, "params": 600603, "time_iter": 13.1154, "accuracy": 0.9644, "precision": 0.6442, "recall": 0.1088, "f1": 0.1861, "auc": 0.7827}
{"epoch": 71, "eta": 376906.3026, "loss": 0.1324, "lr": 0.001, "params": 600603, "time_iter": 13.4639, "accuracy": 0.9638, "precision": 0.6258, "recall": 0.0828, "f1": 0.1462, "auc": 0.7698}
{"epoch": 72, "eta": 363472.9842, "loss": 0.1305, "lr": 0.001, "params": 600603, "time_iter": 13.1541, "accuracy": 0.964, "precision": 0.625, "recall": 0.0974, "f1": 0.1685, "auc": 0.7797}
{"epoch": 73, "eta": 349936.2946, "loss": 0.1303, "lr": 0.001, "params": 600603, "time_iter": 12.8759, "accuracy": 0.964, "precision": 0.6379, "recall": 0.0901, "f1": 0.1579, "auc": 0.7808}
{"epoch": 74, "eta": 336542.2015, "loss": 0.13, "lr": 0.001, "params": 600603, "time_iter": 13.2693, "accuracy": 0.9643, "precision": 0.6686, "recall": 0.095, "f1": 0.1663, "auc": 0.7807}
{"epoch": 75, "eta": 323123.932, "loss": 0.131, "lr": 0.001, "params": 600603, "time_iter": 13.2159, "accuracy": 0.9644, "precision": 0.6802, "recall": 0.095, "f1": 0.1667, "auc": 0.7752}
{"epoch": 76, "eta": 309688.5267, "loss": 0.1298, "lr": 0.001, "params": 600603, "time_iter": 13.1755, "accuracy": 0.9646, "precision": 0.6719, "recall": 0.1047, "f1": 0.1812, "auc": 0.7798}
{"epoch": 77, "eta": 296255.1365, "loss": 0.1312, "lr": 0.001, "params": 600603, "time_iter": 13.1932, "accuracy": 0.9644, "precision": 0.6765, "recall": 0.0933, "f1": 0.1641, "auc": 0.7751}
{"epoch": 78, "eta": 282830.3716, "loss": 0.1302, "lr": 0.001, "params": 600603, "time_iter": 13.2379, "accuracy": 0.9643, "precision": 0.6465, "recall": 0.1039, "f1": 0.179, "auc": 0.7817}
{"epoch": 79, "eta": 269373.3956, "loss": 0.1287, "lr": 0.001, "params": 600603, "time_iter": 13.1318, "accuracy": 0.9645, "precision": 0.6667, "recall": 0.1023, "f1": 0.1773, "auc": 0.7825}
{"epoch": 80, "eta": 255953.9934, "loss": 0.1287, "lr": 0.001, "params": 600603, "time_iter": 13.2932, "accuracy": 0.9647, "precision": 0.6768, "recall": 0.1088, "f1": 0.1874, "auc": 0.7866}
{"epoch": 81, "eta": 242447.4923, "loss": 0.1286, "lr": 0.001, "params": 600603, "time_iter": 12.9356, "accuracy": 0.9645, "precision": 0.657, "recall": 0.1104, "f1": 0.189, "auc": 0.7866}
{"epoch": 82, "eta": 228972.9246, "loss": 0.1283, "lr": 0.001, "params": 600603, "time_iter": 13.0647, "accuracy": 0.9646, "precision": 0.67, "recall": 0.1088, "f1": 0.1872, "auc": 0.7876}
{"epoch": 83, "eta": 215540.0409, "loss": 0.13, "lr": 0.001, "params": 600603, "time_iter": 13.2736, "accuracy": 0.9644, "precision": 0.6784, "recall": 0.0942, "f1": 0.1654, "auc": 0.7844}
{"epoch": 84, "eta": 202076.9063, "loss": 0.1285, "lr": 0.001, "params": 600603, "time_iter": 13.1363, "accuracy": 0.9648, "precision": 0.6814, "recall": 0.1128, "f1": 0.1936, "auc": 0.7838}
{"epoch": 85, "eta": 188631.5771, "loss": 0.1285, "lr": 0.001, "params": 600603, "time_iter": 13.2501, "accuracy": 0.964, "precision": 0.6243, "recall": 0.0958, "f1": 0.1661, "auc": 0.7877}
{"epoch": 86, "eta": 175155.1901, "loss": 0.1289, "lr": 0.001, "params": 600603, "time_iter": 13.0764, "accuracy": 0.964, "precision": 0.631, "recall": 0.0958, "f1": 0.1663, "auc": 0.7876}
{"epoch": 87, "eta": 161693.1955, "loss": 0.1277, "lr": 0.001, "params": 600603, "time_iter": 13.1756, "accuracy": 0.9648, "precision": 0.6798, "recall": 0.112, "f1": 0.1923, "auc": 0.7922}
{"epoch": 88, "eta": 148195.5313, "loss": 0.1301, "lr": 0.001, "params": 600603, "time_iter": 12.912, "accuracy": 0.9646, "precision": 0.7073, "recall": 0.0942, "f1": 0.1662, "auc": 0.7857}
{"epoch": 89, "eta": 134710.7044, "loss": 0.1296, "lr": 0.001, "params": 600603, "time_iter": 12.9833, "accuracy": 0.964, "precision": 0.6379, "recall": 0.0901, "f1": 0.1579, "auc": 0.789}
{"epoch": 90, "eta": 121258.1741, "loss": 0.1289, "lr": 0.001, "params": 600603, "time_iter": 13.2736, "accuracy": 0.9643, "precision": 0.6439, "recall": 0.1071, "f1": 0.1837, "auc": 0.7879}
{"epoch": 91, "eta": 107783.0179, "loss": 0.1296, "lr": 0.001, "params": 600603, "time_iter": 13.0708, "accuracy": 0.9649, "precision": 0.7037, "recall": 0.108, "f1": 0.1872, "auc": 0.7813}
{"epoch": 92, "eta": 94329.3576, "loss": 0.1284, "lr": 0.001, "params": 600603, "time_iter": 13.3413, "accuracy": 0.9645, "precision": 0.6703, "recall": 0.1006, "f1": 0.175, "auc": 0.7884}
{"epoch": 93, "eta": 80842.7574, "loss": 0.1275, "lr": 0.001, "params": 600603, "time_iter": 12.9287, "accuracy": 0.9647, "precision": 0.6875, "recall": 0.1071, "f1": 0.1854, "auc": 0.792}
{"epoch": 94, "eta": 67367.8857, "loss": 0.1273, "lr": 0.001, "params": 600603, "time_iter": 13.0741, "accuracy": 0.9645, "precision": 0.6721, "recall": 0.0998, "f1": 0.1739, "auc": 0.7944}
{"epoch": 95, "eta": 53892.8429, "loss": 0.1278, "lr": 0.001, "params": 600603, "time_iter": 13.0597, "accuracy": 0.9651, "precision": 0.7059, "recall": 0.1169, "f1": 0.2006, "auc": 0.7881}
{"epoch": 96, "eta": 40415.4533, "loss": 0.1273, "lr": 0.001, "params": 600603, "time_iter": 12.9622, "accuracy": 0.9646, "precision": 0.6684, "recall": 0.1063, "f1": 0.1835, "auc": 0.7943}
{"epoch": 97, "eta": 26944.944, "loss": 0.1281, "lr": 0.001, "params": 600603, "time_iter": 13.1545, "accuracy": 0.9647, "precision": 0.6547, "recall": 0.1185, "f1": 0.2007, "auc": 0.7888}
{"epoch": 98, "eta": 13474.6818, "loss": 0.126, "lr": 0.001, "params": 600603, "time_iter": 13.3054, "accuracy": 0.9649, "precision": 0.661, "recall": 0.1266, "f1": 0.2125, "auc": 0.7949}
{"epoch": 99, "eta": 0.0, "loss": 0.1257, "lr": 0.001, "params": 600603, "time_iter": 13.2288, "accuracy": 0.965, "precision": 0.6753, "recall": 0.1266, "f1": 0.2133, "auc": 0.799}
